{
	"name": "DF_for_scd2_full_load",
	"properties": {
		"folder": {
			"name": "SCD"
		},
		"type": "MappingDataFlow",
		"typeProperties": {
			"sources": [
				{
					"dataset": {
						"referenceName": "DS_CSV_test",
						"type": "DatasetReference"
					},
					"name": "scd2Src"
				}
			],
			"sinks": [
				{
					"dataset": {
						"referenceName": "DS_CSV_test",
						"type": "DatasetReference"
					},
					"name": "scd2fullSink"
				}
			],
			"transformations": [
				{
					"name": "derivedColumn1"
				}
			],
			"scriptLines": [
				"source(output(",
				"          EmployeeID as short,",
				"          Name as string,",
				"          Gender as string,",
				"          DateOfBirth as string,",
				"          Department as string,",
				"          JobTitle as string,",
				"          Salary as integer,",
				"          HireDate as string,",
				"          Address as string,",
				"          Email as string,",
				"          PhoneNumber as string,",
				"          MaritalStatus as string,",
				"          EffectiveDate as string,",
				"          EndDate as string",
				"     ),",
				"     allowSchemaDrift: true,",
				"     validateSchema: false,",
				"     ignoreNoFilesFound: false) ~> scd2Src",
				"scd2Src derive(version = 0,",
				"          created_by = 'I2025_JSenthil',",
				"          created_at = currentUTC()) ~> derivedColumn1",
				"derivedColumn1 sink(allowSchemaDrift: true,",
				"     validateSchema: false,",
				"     partitionFileNames:['DIM_scd2_target_employees_v1.csv'],",
				"     skipDuplicateMapInputs: true,",
				"     skipDuplicateMapOutputs: true,",
				"     partitionBy('hash', 1)) ~> scd2fullSink"
			]
		}
	}
}