{
	"name": "PL_ws2_Inc_Load",
	"properties": {
		"activities": [
			{
				"name": "DF_for_transformation",
				"type": "ExecuteDataFlow",
				"state": "Inactive",
				"onInactiveMarkAs": "Succeeded",
				"dependsOn": [],
				"policy": {
					"timeout": "0.12:00:00",
					"retry": 0,
					"retryIntervalInSeconds": 30,
					"secureOutput": false,
					"secureInput": false
				},
				"userProperties": [],
				"typeProperties": {
					"dataflow": {
						"referenceName": "DF_FACT_STTM_DtypeConv",
						"type": "DataFlowReference",
						"datasetParameters": {
							"PatientSrc": {
								"file_name": "SRC PTNT.csv",
								"folder_name": "Workshop 2/SRC_Pharmacy",
								"container_name": "practice-adf"
							},
							"pharmSrc": {
								"file_name": "src_phrmcy.csv",
								"folder_name": "Workshop 2/SRC_Pharmacy",
								"container_name": "practice-adf"
							},
							"YearSrc": {
								"file_name": "Year.csv",
								"folder_name": "Workshop 2/SRC_Pharmacy",
								"container_name": "practice-adf"
							},
							"SinkToBlob": {
								"file_name": "STTM_PTNT_STG.csv",
								"folder_name": "ETL_stuff",
								"container_name": "csvcontainer"
							}
						}
					},
					"compute": {
						"coreCount": 8,
						"computeType": "General"
					},
					"traceLevel": "Fine"
				}
			},
			{
				"name": "CP_stg_to_sqlserver",
				"type": "Copy",
				"state": "Inactive",
				"onInactiveMarkAs": "Succeeded",
				"dependsOn": [
					{
						"activity": "DF_for_transformation",
						"dependencyConditions": [
							"Succeeded"
						]
					}
				],
				"policy": {
					"timeout": "0.12:00:00",
					"retry": 0,
					"retryIntervalInSeconds": 30,
					"secureOutput": false,
					"secureInput": false
				},
				"userProperties": [],
				"typeProperties": {
					"source": {
						"type": "DelimitedTextSource",
						"storeSettings": {
							"type": "AzureBlobStorageReadSettings",
							"recursive": true,
							"enablePartitionDiscovery": false
						},
						"formatSettings": {
							"type": "DelimitedTextReadSettings"
						}
					},
					"sink": {
						"type": "SqlServerSink",
						"writeBehavior": "insert",
						"sqlWriterUseTableLock": false
					},
					"enableStaging": false,
					"translator": {
						"type": "TabularTranslator",
						"typeConversion": true,
						"typeConversionSettings": {
							"allowDataTruncation": true,
							"treatBooleanAsNumber": false
						}
					}
				},
				"inputs": [
					{
						"referenceName": "DS_CSV_test",
						"type": "DatasetReference",
						"parameters": {
							"file_name": "STTM_PTNT_STG.csv",
							"folder_name": "ETL_stuff",
							"container_name": "csvcontainer"
						}
					}
				],
				"outputs": [
					{
						"referenceName": "DS_Sql_server_intern",
						"type": "DatasetReference",
						"parameters": {
							"DatabaseObject": "I2025_JSenthil",
							"TableName": "STG_FACT_DSPN_ADF"
						}
					}
				]
			},
			{
				"name": "Script1",
				"type": "Script",
				"state": "Inactive",
				"onInactiveMarkAs": "Succeeded",
				"dependsOn": [
					{
						"activity": "CP_stg_to_sqlserver",
						"dependencyConditions": [
							"Succeeded"
						]
					}
				],
				"policy": {
					"timeout": "0.12:00:00",
					"retry": 0,
					"retryIntervalInSeconds": 30,
					"secureOutput": false,
					"secureInput": false
				},
				"userProperties": [],
				"linkedServiceName": {
					"referenceName": "LS_SQL_server",
					"type": "LinkedServiceReference"
				},
				"typeProperties": {
					"scripts": [
						{
							"type": "Query",
							"text": ""
						}
					],
					"scriptBlockExecutionTimeout": "02:00:00"
				}
			},
			{
				"name": "LU_get_max_tgt_trans_date",
				"type": "Lookup",
				"dependsOn": [],
				"policy": {
					"timeout": "0.12:00:00",
					"retry": 0,
					"retryIntervalInSeconds": 30,
					"secureOutput": false,
					"secureInput": false
				},
				"userProperties": [],
				"typeProperties": {
					"source": {
						"type": "SqlServerSource",
						"sqlReaderQuery": "SELECT MAX(TRANS_DATE)\nFROM FACT_DSPN",
						"queryTimeout": "02:00:00",
						"partitionOption": "None"
					},
					"dataset": {
						"referenceName": "DS_Sql_server_intern",
						"type": "DatasetReference",
						"parameters": {
							"DatabaseObject": "I2025_JSenthil",
							"TableName": "TGT_FACT_DSPN_ADF"
						}
					}
				}
			},
			{
				"name": "SET_max_date",
				"type": "SetVariable",
				"dependsOn": [
					{
						"activity": "LU_get_max_tgt_trans_date",
						"dependencyConditions": [
							"Succeeded"
						]
					}
				],
				"policy": {
					"secureOutput": false,
					"secureInput": false
				},
				"userProperties": [],
				"typeProperties": {
					"variableName": "max_date",
					"value": {
						"value": "@activity('LU_get_max_tgt_trans_date').output.firstRow['']",
						"type": "Expression"
					}
				}
			}
		],
		"variables": {
			"max_date": {
				"type": "String"
			}
		},
		"folder": {
			"name": "Workshop 2"
		},
		"annotations": []
	}
}